{
    "metadata-entries": [
        {
            "id": "CLIENT-SIDE-DEV",
            "displayName": "Client-Side Technology",
            "description": "Used technology for the client-side code",
            "values": [
                "JavaScript","TypeScript","React","Angular","Handlebars","Vue.js","Other"
            ]            
        },
        {
            "id": "BOT-FRAMEWORK-VERSION",
            "displayName": "Bot Framework Version",
            "description": "Used Bot Framework version",
            "values": [
                "bot40","bot30","other"
            ]
        },
        {
            "id": "SPFX-VERSION",
            "displayName": "SharePoint Framework version",
            "description": "Used SharePoint Framework version",
            "values": [
                "1.0.0","1.1.0","1.3.0","1.4.0","1.4.1","1.5.0","1.5.1","1.6.0","1.7.0","1.7.1","1.8.0","1.8.1","1.8.2","1.9.1","1.10.0","1.11.0"
            ]
        },
        {
            "id": "GRAPH-APIS",
            "displayName": "Used Microsoft Graph APIs",
            "description": "List of used Microsoft Graph APIs",
            "values": [
                "sites","files","teams","mail","users","groups","identity","others"
            ]
        },
        {
            "id": "GRAPH-TOOLKIT-CONTROLS",
            "displayName": "Used Microsoft Graph Toolkit Controls",
            "description": "List of used Microsoft Graph Toolkit Controls",
            "values": [
                "login","get","person","people","personCard","peoplePicker","teamsChannelPicker","agenda","tasks","todo","other"
            ]
        }
    ]
}